{
  "activity_name": "com.bork.dsp.datuna/com.bork.dsp.datuna.DaTunaTuner", 
  "activity": {
    "root": {
      "scrollable-horizontal": false, 
      "draw": true, 
      "ancestors": [
        "android.widget.FrameLayout", 
        "android.view.ViewGroup", 
        "android.view.View", 
        "java.lang.Object"
      ], 
      "clickable": false, 
      "pressed": "not_pressed", 
      "focusable": false, 
      "long-clickable": false, 
      "enabled": true, 
      "bounds": [
        0, 
        0, 
        1440, 
        2392
      ], 
      "visibility": "visible", 
      "content-desc": [
        null
      ], 
      "rel-bounds": [
        0, 
        0, 
        1440, 
        2392
      ], 
      "focused": false, 
      "selected": false, 
      "scrollable-vertical": false, 
      "children": [
        {
          "resource-id": "android:id/decor_content_parent", 
          "adapter-view": false, 
          "pointer": "e10a95a", 
          "children": [
            {
              "resource-id": "android:id/content", 
              "adapter-view": false, 
              "pointer": "64db78b", 
              "children": [
                {
                  "scrollable-horizontal": false, 
                  "draw": true, 
                  "ancestors": [
                    "android.view.ViewGroup", 
                    "android.view.View", 
                    "java.lang.Object"
                  ], 
                  "clickable": false, 
                  "pressed": "not_pressed", 
                  "focusable": false, 
                  "long-clickable": false, 
                  "enabled": true, 
                  "bounds": [
                    0, 
                    189, 
                    1440, 
                    2392
                  ], 
                  "visibility": "visible", 
                  "content-desc": [
                    null
                  ], 
                  "rel-bounds": [
                    0, 
                    0, 
                    1440, 
                    2203
                  ], 
                  "focused": false, 
                  "selected": false, 
                  "scrollable-vertical": false, 
                  "children": [
                    {
                      "resource-id": "com.bork.dsp.datuna:id/adView", 
                      "adapter-view": false, 
                      "pointer": "61bfc81", 
                      "scrollable-horizontal": false, 
                      "ancestors": [
                        "android.view.View", 
                        "java.lang.Object"
                      ], 
                      "selected": false, 
                      "content-desc": [
                        null
                      ], 
                      "rel-bounds": [
                        0, 
                        0, 
                        1440, 
                        4
                      ], 
                      "draw": false, 
                      "focusable": false, 
                      "long-clickable": false, 
                      "visibility": "visible", 
                      "focused": false, 
                      "clickable": false, 
                      "abs-pos": true, 
                      "class": "android.widget.ImageView", 
                      "visible-to-user": true, 
                      "package": "com.bork.dsp.datuna", 
                      "enabled": true, 
                      "bounds": [
                        0, 
                        189, 
                        1440, 
                        193
                      ], 
                      "pressed": "not_pressed", 
                      "scrollable-vertical": false
                    }, 
                    {
                      "resource-id": "com.bork.dsp.datuna:id/datuna", 
                      "adapter-view": false, 
                      "pointer": "da00126", 
                      "scrollable-horizontal": false, 
                      "ancestors": [
                        "android.widget.ImageView", 
                        "android.view.View", 
                        "java.lang.Object"
                      ], 
                      "selected": false, 
                      "content-desc": [
                        null
                      ], 
                      "rel-bounds": [
                        0, 
                        4, 
                        1440, 
                        2203
                      ], 
                      "draw": false, 
                      "focusable": true, 
                      "long-clickable": true, 
                      "visibility": "visible", 
                      "focused": false, 
                      "clickable": false, 
                      "abs-pos": true, 
                      "class": "com.bork.dsp.datuna.DaTunaViewSurface", 
                      "visible-to-user": true, 
                      "package": "com.bork.dsp.datuna", 
                      "enabled": true, 
                      "bounds": [
                        0, 
                        193, 
                        1440, 
                        2392
                      ], 
                      "pressed": "not_pressed", 
                      "scrollable-vertical": false
                    }
                  ], 
                  "adapter-view": false, 
                  "abs-pos": true, 
                  "pointer": "d85b068", 
                  "class": "android.widget.RelativeLayout", 
                  "visible-to-user": true
                }
              ], 
              "scrollable-horizontal": false, 
              "ancestors": [
                "android.view.ViewGroup", 
                "android.view.View", 
                "java.lang.Object"
              ], 
              "selected": false, 
              "content-desc": [
                null
              ], 
              "rel-bounds": [
                0, 
                189, 
                1440, 
                2392
              ], 
              "draw": true, 
              "focusable": false, 
              "long-clickable": false, 
              "visibility": "visible", 
              "focused": false, 
              "clickable": false, 
              "abs-pos": true, 
              "class": "android.widget.FrameLayout", 
              "visible-to-user": true, 
              "package": "android", 
              "enabled": true, 
              "bounds": [
                0, 
                189, 
                1440, 
                2392
              ], 
              "pressed": "not_pressed", 
              "scrollable-vertical": false
            }, 
            {
              "resource-id": "android:id/action_bar_container", 
              "adapter-view": false, 
              "pointer": "6de4167", 
              "children": [
                {
                  "resource-id": "android:id/action_bar", 
                  "adapter-view": false, 
                  "pointer": "1396b14", 
                  "children": [
                    {
                      "scrollable-horizontal": false, 
                      "draw": true, 
                      "ancestors": [
                        "android.view.ViewGroup", 
                        "android.view.View", 
                        "java.lang.Object"
                      ], 
                      "clickable": true, 
                      "pressed": "not_pressed", 
                      "focusable": false, 
                      "long-clickable": false, 
                      "enabled": false, 
                      "bounds": [
                        29, 
                        84, 
                        558, 
                        189
                      ], 
                      "visibility": "visible", 
                      "content-desc": [
                        null
                      ], 
                      "rel-bounds": [
                        29, 
                        0, 
                        558, 
                        105
                      ], 
                      "focused": false, 
                      "selected": false, 
                      "scrollable-vertical": false, 
                      "children": [
                        {
                          "scrollable-horizontal": false, 
                          "draw": true, 
                          "ancestors": [
                            "android.widget.FrameLayout", 
                            "android.view.ViewGroup", 
                            "android.view.View", 
                            "java.lang.Object"
                          ], 
                          "clickable": false, 
                          "pressed": "not_pressed", 
                          "focusable": false, 
                          "long-clickable": false, 
                          "enabled": true, 
                          "bounds": [
                            29, 
                            84, 
                            106, 
                            189
                          ], 
                          "visibility": "visible", 
                          "content-desc": [
                            null
                          ], 
                          "rel-bounds": [
                            0, 
                            0, 
                            77, 
                            105
                          ], 
                          "focused": false, 
                          "selected": false, 
                          "scrollable-vertical": false, 
                          "children": [
                            {
                              "resource-id": "android:id/up", 
                              "adapter-view": false, 
                              "pointer": "8038d03", 
                              "scrollable-horizontal": false, 
                              "ancestors": [
                                "android.view.View", 
                                "java.lang.Object"
                              ], 
                              "selected": false, 
                              "content-desc": [
                                null
                              ], 
                              "rel-bounds": [
                                0, 
                                0, 
                                0, 
                                0
                              ], 
                              "draw": false, 
                              "focusable": false, 
                              "long-clickable": false, 
                              "visibility": "gone", 
                              "focused": false, 
                              "clickable": false, 
                              "abs-pos": true, 
                              "class": "android.widget.ImageView", 
                              "visible-to-user": false, 
                              "package": "android", 
                              "enabled": true, 
                              "bounds": [
                                29, 
                                84, 
                                29, 
                                84
                              ], 
                              "pressed": "not_pressed", 
                              "scrollable-vertical": false
                            }, 
                            {
                              "resource-id": "android:id/home", 
                              "adapter-view": false, 
                              "pointer": "1cc2480", 
                              "scrollable-horizontal": false, 
                              "ancestors": [
                                "android.view.View", 
                                "java.lang.Object"
                              ], 
                              "selected": false, 
                              "content-desc": [
                                null
                              ], 
                              "rel-bounds": [
                                14, 
                                28, 
                                63, 
                                77
                              ], 
                              "draw": false, 
                              "focusable": false, 
                              "long-clickable": false, 
                              "visibility": "visible", 
                              "focused": false, 
                              "clickable": false, 
                              "abs-pos": true, 
                              "class": "android.widget.ImageView", 
                              "visible-to-user": true, 
                              "package": "android", 
                              "enabled": true, 
                              "bounds": [
                                43, 
                                112, 
                                92, 
                                161
                              ], 
                              "pressed": "not_pressed", 
                              "scrollable-vertical": false
                            }
                          ], 
                          "adapter-view": false, 
                          "abs-pos": true, 
                          "pointer": "97b09b2", 
                          "class": "com.android.internal.widget.ActionBarView$HomeView", 
                          "visible-to-user": true
                        }, 
                        {
                          "scrollable-horizontal": false, 
                          "draw": true, 
                          "ancestors": [
                            "android.view.ViewGroup", 
                            "android.view.View", 
                            "java.lang.Object"
                          ], 
                          "clickable": false, 
                          "pressed": "not_pressed", 
                          "focusable": false, 
                          "long-clickable": false, 
                          "enabled": true, 
                          "bounds": [
                            106, 
                            94, 
                            558, 
                            179
                          ], 
                          "visibility": "visible", 
                          "content-desc": [
                            null
                          ], 
                          "rel-bounds": [
                            77, 
                            10, 
                            529, 
                            95
                          ], 
                          "focused": false, 
                          "selected": false, 
                          "scrollable-vertical": false, 
                          "children": [
                            {
                              "text": "Lite: Chromatic", 
                              "resource-id": "android:id/action_bar_title", 
                              "adapter-view": false, 
                              "pointer": "78c0efe", 
                              "scrollable-horizontal": false, 
                              "ancestors": [
                                "android.view.View", 
                                "java.lang.Object"
                              ], 
                              "selected": false, 
                              "content-desc": [
                                null
                              ], 
                              "rel-bounds": [
                                0, 
                                0, 
                                424, 
                                85
                              ], 
                              "draw": false, 
                              "focusable": false, 
                              "long-clickable": false, 
                              "visibility": "visible", 
                              "focused": false, 
                              "clickable": false, 
                              "abs-pos": true, 
                              "class": "android.widget.TextView", 
                              "visible-to-user": true, 
                              "package": "android", 
                              "enabled": true, 
                              "bounds": [
                                106, 
                                94, 
                                530, 
                                179
                              ], 
                              "pressed": "not_pressed", 
                              "scrollable-vertical": false
                            }, 
                            {
                              "text": "", 
                              "resource-id": "android:id/action_bar_subtitle", 
                              "adapter-view": false, 
                              "pointer": "9a7f65f", 
                              "scrollable-horizontal": false, 
                              "ancestors": [
                                "android.view.View", 
                                "java.lang.Object"
                              ], 
                              "selected": false, 
                              "content-desc": [
                                null
                              ], 
                              "rel-bounds": [
                                0, 
                                0, 
                                0, 
                                0
                              ], 
                              "draw": false, 
                              "focusable": false, 
                              "long-clickable": false, 
                              "visibility": "gone", 
                              "focused": false, 
                              "clickable": false, 
                              "abs-pos": true, 
                              "class": "android.widget.TextView", 
                              "visible-to-user": false, 
                              "package": "android", 
                              "enabled": true, 
                              "bounds": [
                                106, 
                                94, 
                                106, 
                                94
                              ], 
                              "pressed": "not_pressed", 
                              "scrollable-vertical": false
                            }
                          ], 
                          "adapter-view": false, 
                          "abs-pos": true, 
                          "pointer": "20abab9", 
                          "class": "android.widget.LinearLayout", 
                          "visible-to-user": true
                        }
                      ], 
                      "adapter-view": false, 
                      "abs-pos": true, 
                      "pointer": "98adfbd", 
                      "class": "android.widget.LinearLayout", 
                      "visible-to-user": true
                    }, 
                    {
                      "scrollable-horizontal": false, 
                      "draw": false, 
                      "ancestors": [
                        "android.widget.LinearLayout", 
                        "android.view.ViewGroup", 
                        "android.view.View", 
                        "java.lang.Object"
                      ], 
                      "clickable": false, 
                      "pressed": "not_pressed", 
                      "focusable": false, 
                      "long-clickable": false, 
                      "enabled": true, 
                      "bounds": [
                        1244, 
                        84, 
                        1440, 
                        189
                      ], 
                      "visibility": "visible", 
                      "content-desc": [
                        null
                      ], 
                      "rel-bounds": [
                        1244, 
                        0, 
                        1440, 
                        105
                      ], 
                      "focused": false, 
                      "selected": false, 
                      "scrollable-vertical": false, 
                      "children": [
                        {
                          "scrollable-horizontal": false, 
                          "draw": false, 
                          "ancestors": [
                            "android.widget.ImageButton", 
                            "android.widget.ImageView", 
                            "android.view.View", 
                            "java.lang.Object"
                          ], 
                          "clickable": true, 
                          "pressed": "not_pressed", 
                          "focusable": true, 
                          "long-clickable": false, 
                          "enabled": true, 
                          "bounds": [
                            1244, 
                            84, 
                            1440, 
                            189
                          ], 
                          "visibility": "visible", 
                          "content-desc": [
                            "More options"
                          ], 
                          "rel-bounds": [
                            0, 
                            0, 
                            196, 
                            105
                          ], 
                          "focused": false, 
                          "selected": false, 
                          "scrollable-vertical": false, 
                          "adapter-view": false, 
                          "abs-pos": true, 
                          "pointer": "a134975", 
                          "class": "android.widget.ActionMenuPresenter$OverflowMenuButton", 
                          "visible-to-user": true
                        }
                      ], 
                      "adapter-view": false, 
                      "abs-pos": true, 
                      "pointer": "60f08ac", 
                      "class": "android.widget.ActionMenuView", 
                      "visible-to-user": true
                    }
                  ], 
                  "scrollable-horizontal": false, 
                  "ancestors": [
                    "com.android.internal.widget.AbsActionBarView", 
                    "android.view.ViewGroup", 
                    "android.view.View", 
                    "java.lang.Object"
                  ], 
                  "selected": false, 
                  "content-desc": [
                    null
                  ], 
                  "rel-bounds": [
                    0, 
                    0, 
                    1440, 
                    105
                  ], 
                  "draw": true, 
                  "focusable": false, 
                  "long-clickable": false, 
                  "visibility": "visible", 
                  "focused": false, 
                  "clickable": false, 
                  "abs-pos": true, 
                  "class": "com.android.internal.widget.ActionBarView", 
                  "visible-to-user": true, 
                  "package": "android", 
                  "enabled": true, 
                  "bounds": [
                    0, 
                    84, 
                    1440, 
                    189
                  ], 
                  "pressed": "not_pressed", 
                  "scrollable-vertical": false
                }, 
                {
                  "resource-id": "android:id/action_context_bar", 
                  "adapter-view": false, 
                  "pointer": "161d0a", 
                  "scrollable-horizontal": false, 
                  "ancestors": [
                    "com.android.internal.widget.AbsActionBarView", 
                    "android.view.ViewGroup", 
                    "android.view.View", 
                    "java.lang.Object"
                  ], 
                  "selected": false, 
                  "content-desc": [
                    null
                  ], 
                  "rel-bounds": [
                    0, 
                    0, 
                    0, 
                    0
                  ], 
                  "draw": true, 
                  "focusable": false, 
                  "long-clickable": false, 
                  "visibility": "gone", 
                  "focused": false, 
                  "clickable": false, 
                  "abs-pos": true, 
                  "class": "com.android.internal.widget.ActionBarContextView", 
                  "visible-to-user": false, 
                  "package": "android", 
                  "enabled": true, 
                  "bounds": [
                    0, 
                    84, 
                    0, 
                    84
                  ], 
                  "pressed": "not_pressed", 
                  "scrollable-vertical": false
                }
              ], 
              "scrollable-horizontal": false, 
              "ancestors": [
                "android.widget.FrameLayout", 
                "android.view.ViewGroup", 
                "android.view.View", 
                "java.lang.Object"
              ], 
              "selected": false, 
              "content-desc": [
                null
              ], 
              "rel-bounds": [
                0, 
                84, 
                1440, 
                189
              ], 
              "draw": false, 
              "focusable": false, 
              "long-clickable": false, 
              "visibility": "visible", 
              "focused": false, 
              "clickable": false, 
              "abs-pos": true, 
              "class": "com.android.internal.widget.ActionBarContainer", 
              "visible-to-user": true, 
              "package": "android", 
              "enabled": true, 
              "bounds": [
                0, 
                84, 
                1440, 
                189
              ], 
              "pressed": "not_pressed", 
              "scrollable-vertical": false
            }, 
            {
              "resource-id": "android:id/split_action_bar", 
              "adapter-view": false, 
              "pointer": "5ff997b", 
              "scrollable-horizontal": false, 
              "ancestors": [
                "android.widget.FrameLayout", 
                "android.view.ViewGroup", 
                "android.view.View", 
                "java.lang.Object"
              ], 
              "selected": false, 
              "content-desc": [
                null
              ], 
              "rel-bounds": [
                0, 
                0, 
                0, 
                0
              ], 
              "draw": false, 
              "focusable": false, 
              "long-clickable": false, 
              "visibility": "gone", 
              "focused": false, 
              "clickable": false, 
              "abs-pos": true, 
              "class": "com.android.internal.widget.ActionBarContainer", 
              "visible-to-user": false, 
              "package": "android", 
              "enabled": true, 
              "bounds": [
                0, 
                0, 
                0, 
                0
              ], 
              "pressed": "not_pressed", 
              "scrollable-vertical": false
            }
          ], 
          "scrollable-horizontal": false, 
          "ancestors": [
            "android.view.ViewGroup", 
            "android.view.View", 
            "java.lang.Object"
          ], 
          "selected": false, 
          "content-desc": [
            null
          ], 
          "rel-bounds": [
            0, 
            0, 
            1440, 
            2392
          ], 
          "draw": true, 
          "focusable": false, 
          "long-clickable": false, 
          "visibility": "visible", 
          "focused": false, 
          "clickable": false, 
          "abs-pos": true, 
          "class": "com.android.internal.widget.ActionBarOverlayLayout", 
          "visible-to-user": true, 
          "package": "android", 
          "enabled": true, 
          "bounds": [
            0, 
            0, 
            1440, 
            2392
          ], 
          "pressed": "not_pressed", 
          "scrollable-vertical": false
        }
      ], 
      "adapter-view": false, 
      "abs-pos": true, 
      "pointer": "28a1505", 
      "class": "com.android.internal.policy.PhoneWindow$DecorView", 
      "visible-to-user": true
    }, 
    "added_fragments": [], 
    "active_fragments": []
  }, 
  "is_keyboard_deployed": false, 
  "request_id": "599"
}